{
    "apiVersion": 2,
    "name": "gutenverse/post-comment",
    "class_callback": "\\Gutenverse\\Block\\Post_Comment",
    "title": "Gutenverse Post Comment",
    "description": "Show comment section of a single post.",
    "category": "gutenverse-post",
    "attributes": {
        "elementId": {
            "type": "string"
        },
        "postId": {
            "type": "string",
            "default": 0
        },
        "backendPostId": {
            "type": "string"
        },
        "noContentText": {
            "type": "string",
            "default": "No Content"
        },
        "background": {
            "type": "object"
        },
        "backgroundHover": {
            "type": "object"
        },
        "border": {
            "type": "object"
        },
        "boxShadow": {
            "type": "object"
        },
        "borderHover": {
            "type": "object"
        },
        "boxShadowHover": {
            "type": "object"
        },
        "margin": {
            "type": "object"
        },
        "padding": {
            "type": "object"
        },
        "zIndex": {
            "type": "object"
        },
        "animation": {
            "type": "object"
        },
        "hideDesktop": {
            "type": "boolean"
        },
        "hideTablet": {
            "type": "boolean"
        },
        "hideMobile": {
            "type": "boolean"
        }
    },
    "supports": {
        "className": false
    },
    "keywords": [
        "post",
        "comment"
    ]
}